jobsparser/__init__.py
jobsparser/__main__.py
jobsparser/cli.py
jobsparser-0.1.13.dist-info/METADATA
jobsparser-0.1.13.dist-info/WHEEL
jobsparser-0.1.13.dist-info/entry_points.txt
jobsparser-0.1.13.dist-info/RECORD
