Metadata-Version: 2.4
Name: jobsparser
Version: 0.1.13
Summary: CLI tool to scrape jobs from multiple job sites
Project-URL: Repository, https://github.com/FranciscoMoretti/jobsparser
Author: FranciscoMoretti
License-Expression: MIT
Keywords: cli,glassdoor,indeed,jobs,linkedin,scraping
Classifier: Development Status :: 4 - Beta
Classifier: Environment :: Console
Classifier: Intended Audience :: End Users/Desktop
Classifier: License :: OSI Approved :: MIT License
Classifier: Programming Language :: Python :: 3
Classifier: Programming Language :: Python :: 3.10
Classifier: Topic :: Internet :: WWW/HTTP :: Dynamic Content
Requires-Python: >=3.10
Requires-Dist: click>=8.0.0
Requires-Dist: jobspy2>=0.0.8
Requires-Dist: pandas>=2.0.0
